{
  "megacloud": {
    "anime": {
      "key": "1c2b9fb9333a315c956276ed0a56943e472920b6b6d66f5e6cbf458ae782232f",
      "hash": "773ee2e1",
      "last_updated": {
        "timestamp": 1751728281386,
        "time": "July 5, 2025 at 03:11 PM"
      }
    },
    "movie": {
      "key": "fecb7d9d01a6b5b4645d25b39b5a639615018752d3903e87af64c1eaa2c7316b",
      "hash": "3c2f81cf",
      "last_updated": {
        "timestamp": 1751753462611,
        "time": "July 5, 2025 at 10:11 PM"
      }
    }
  },
  "videostr": {
    "anime": {
      "key": "1c2b9fb9333a315c956276ed0a56943e472920b6b6d66f5e6cbf458ae782232f",
      "hash": "773ee2e1",
      "last_updated": {
        "timestamp": 1751728281487,
        "time": "July 5, 2025 at 03:11 PM"
      }
    },
    "movie": {
      "key": "fecb7d9d01a6b5b4645d25b39b5a639615018752d3903e87af64c1eaa2c7316b",
      "hash": "3c2f81cf",
      "last_updated": {
        "timestamp": 1751753462511,
        "time": "July 5, 2025 at 10:11 PM"
      }
    }
  },
  "cloudvidz": {
    "anime": {
      "key": "KfsbLyD0vy7OpKZZyfBhMUcvdHLxNMjkw7XsUeEODpLAQmljr",
      "hash": "b2b01e18",
      "last_updated": {
        "timestamp": 1751735422377,
        "time": "July 5, 2025 at 05:10 PM"
      }
    },
    "movie": {
      "key": "8xt6vkLT57TUgc1Zm3lHyKA9mXchfCyTdm14t2dfP7HI8QunM1yRT27KZMU",
      "hash": "fe6686d7",
      "last_updated": {
        "timestamp": 1751742598700,
        "time": "July 5, 2025 at 07:09 PM"
      }
    }
  },
  "cdnstreame": {
    "anime": {
      "key": "KfsbLyD0vy7OpKZZyfBhMUcvdHLxNMjkw7XsUeEODpLAQmljr",
      "hash": "b2b01e18",
      "last_updated": {
        "timestamp": 1751735422428,
        "time": "July 5, 2025 at 05:10 PM"
      }
    },
    "movie": {
      "key": "8xt6vkLT57TUgc1Zm3lHyKA9mXchfCyTdm14t2dfP7HI8QunM1yRT27KZMU",
      "hash": "fe6686d7",
      "last_updated": {
        "timestamp": 1751742598753,
        "time": "July 5, 2025 at 07:09 PM"
      }
    }
  },
  "streameeeeee": {
    "anime": {
      "key": "KfsbLyD0vy7OpKZZyfBhMUcvdHLxNMjkw7XsUeEODpLAQmljr",
      "hash": "b2b01e18",
      "last_updated": {
        "timestamp": 1751735421990,
        "time": "July 5, 2025 at 05:10 PM"
      }
    },
    "movie": {
      "key": "8xt6vkLT57TUgc1Zm3lHyKA9mXchfCyTdm14t2dfP7HI8QunM1yRT27KZMU",
      "hash": "fe6686d7",
      "last_updated": {
        "timestamp": 1751742598154,
        "time": "July 5, 2025 at 07:09 PM"
      }
    }
  }
}