{
  "megacloud": {
    "anime": {
      "key": "e2502a7fc985ee38e0d31e5171d36bbf8d480370530d6ab685a6718a686035c7",
      "hash": "4821b2b0",
      "last_updated": {
        "timestamp": 1752031032553,
        "time": "July 9, 2025 at 03:17 AM"
      }
    },
    "movie": {
      "key": "16ab7478a70b5ebceefeac69dc4a2b9a2390e3a44be6b51ad485fc8d8ab2969d",
      "hash": "def7dfb",
      "last_updated": {
        "timestamp": 1752031032306,
        "time": "July 9, 2025 at 03:17 AM"
      }
    }
  },
  "videostr": {
    "anime": {
      "key": "e2502a7fc985ee38e0d31e5171d36bbf8d480370530d6ab685a6718a686035c7",
      "hash": "4821b2b0",
      "last_updated": {
        "timestamp": 1752031032645,
        "time": "July 9, 2025 at 03:17 AM"
      }
    },
    "movie": {
      "key": "16ab7478a70b5ebceefeac69dc4a2b9a2390e3a44be6b51ad485fc8d8ab2969d",
      "hash": "def7dfb",
      "last_updated": {
        "timestamp": 1752031032546,
        "time": "July 9, 2025 at 03:17 AM"
      }
    }
  },
  "cloudvidz": {
    "anime": {
      "key": "a7Z5Lqfg92B0GPjTaH2gJlckv8LvryMmLNwuHkYvV7",
      "hash": "ecbb90c",
      "last_updated": {
        "timestamp": 1752031032682,
        "time": "July 9, 2025 at 03:17 AM"
      }
    },
    "movie": {
      "key": "94wK0fxDn72AgwY05hXb1Mfk1WihM63uge32fmBp12",
      "hash": "d8d490d7",
      "last_updated": {
        "timestamp": 1752012763373,
        "time": "July 8, 2025 at 10:12 PM"
      }
    }
  },
  "cdnstreame": {
    "anime": {
      "key": "a7Z5Lqfg92B0GPjTaH2gJlckv8LvryMmLNwuHkYvV7",
      "hash": "ecbb90c",
      "last_updated": {
        "timestamp": 1752031032690,
        "time": "July 9, 2025 at 03:17 AM"
      }
    },
    "movie": {
      "key": "94wK0fxDn72AgwY05hXb1Mfk1WihM63uge32fmBp12",
      "hash": "d8d490d7",
      "last_updated": {
        "timestamp": 1752012763381,
        "time": "July 8, 2025 at 10:12 PM"
      }
    }
  },
  "streameeeeee": {
    "anime": {
      "key": "a7Z5Lqfg92B0GPjTaH2gJlckv8LvryMmLNwuHkYvV7",
      "hash": "ecbb90c",
      "last_updated": {
        "timestamp": 1752031032438,
        "time": "July 9, 2025 at 03:17 AM"
      }
    },
    "movie": {
      "key": "94wK0fxDn72AgwY05hXb1Mfk1WihM63uge32fmBp12",
      "hash": "d8d490d7",
      "last_updated": {
        "timestamp": 1752012762925,
        "time": "July 8, 2025 at 10:12 PM"
      }
    }
  }
}